design.sv
// Code your design here
module voter_if (In, Out);
  
  input [3:0] In; 
  
  output [3:1] Out; 
  
  reg [3:1] Out;

  always@ (In)
    
    case (In)    
      
    4'b0000 :
      
   	begin
      
        Out[3] = 1;
      	Out[2] = 0;
      	Out[1] = 0;
      
   	end
      
    4'b0001 :
        Out[3] = 1;
    4'b0010 :
        Out[3] = 1;
    4'b0100 :
        Out[3] = 1;
    4'b1000 :
        Out[3] = 1;
  
    4'b0011 :
        Out[2] = 1;
    4'b0110 :
        Out[2] = 1;
    4'b1100 :
        Out[2] = 1;
    4'b1001 :
        Out[2] = 1;
    4'b1010 :
        Out[2] = 1;
    4'b0101 :
        Out[2] = 1;
  
    4'b1110 :
        Out[1] = 1;
    4'b1101 :
        Out[1] = 1;
    4'b1011 :
        Out[1] = 1;
    4'b0111 :
        Out[1] = 1;
    4'b1111 :
        Out[1] = 1;
      
    default;
      
endcase
  
endmodule

testbench.sv
// Code your testbench here
// or browse Examples
module voter_if_tb;
  
  reg [3:0] In_;
  
  wire  [3:1] Out_;
  
  voter_if voter_1(.In(In_),.Out(Out_));
  
initial
  
begin
    #150 $finish;
  
end
  
initial
  
begin
  
    #0   In_ = 4'b0000;
    #10  In_ = 4'b0001;
    #10  In_ = 4'b0010;
    #10  In_ = 4'b0011;
    #10  In_ = 4'b0100;
    #10  In_ = 4'b0101;
    #10  In_ = 4'b0110;
    #10  In_ = 4'b0111;
    #10  In_ = 4'b1000;
    #10  In_ = 4'b1001;
    #10  In_ = 4'b1010;
    #10  In_ = 4'b1011;
    #10  In_ = 4'b1100;
    #10  In_ = 4'b1101;
    #10  In_ = 4'b1110;
    #10  In_ = 4'b1111;
  
end
  
initial
  
begin
    $dumpfile("WDTM.vcd");
    $dumpvars(0, voter_1);
end
  
endmodule

WDTM.vcd
$date
	Sat Apr 23 15:10:16 2022
$end
$version
	Icarus Verilog
$end
$timescale
	1s
$end
$scope module voter_if_tb $end
$scope module voter_1 $end
$var wire 4 ! In [3:0] $end
$var reg 3 " Out [3:1] $end
$upscope $end
$upscope $end
$enddefinitions $end
#0
$dumpvars
b100 "
b0 !
$end
#10
b1 !
#20
b10 !
#30
b110 "
b11 !
#40
b100 !
#50
b101 !
#60
b110 !
#70
b111 "
b111 !
#80
b1000 !
#90
b1001 !
#100
b1010 !
#110
b1011 !
#120
b1100 !
#130
b1101 !
#140
b1110 !
#150
b1111 !
